setup.py
jobexcel/__init__.py
jobexcel/excel.py
jobexcel.egg-info/PKG-INFO
jobexcel.egg-info/SOURCES.txt
jobexcel.egg-info/dependency_links.txt
jobexcel.egg-info/requires.txt
jobexcel.egg-info/top_level.txt
jobexcel.egg-info/zip-safe