Metadata-Version: 1.1
Name: jobexcel
Version: 0.1.1
Summary: haibo universal function
Home-page: hbnnlove.sinaapp.com
Author: haibo
Author-email: hbnnlong@163.com
License: MIT
Keywords: jobexcel function
Platform: any
Classifier: License :: OSI Approved :: MIT License
Classifier: Programming Language :: Python
Classifier: Intended Audience :: Developers
Classifier: Operating System :: OS Independent
